fiduswriter/gitrepo_export/__init__.py
fiduswriter/gitrepo_export/admin.py
fiduswriter/gitrepo_export/apps.py
fiduswriter/gitrepo_export/models.py
fiduswriter/gitrepo_export/urls.py
fiduswriter/gitrepo_export/views.py
fiduswriter/gitrepo_export/helpers/__init__.py
fiduswriter/gitrepo_export/helpers/github.py
fiduswriter/gitrepo_export/helpers/gitlab.py
fiduswriter/gitrepo_export/locale/bg/LC_MESSAGES/djangojs.mo
fiduswriter/gitrepo_export/locale/bg/LC_MESSAGES/djangojs.po
fiduswriter/gitrepo_export/locale/de/LC_MESSAGES/djangojs.mo
fiduswriter/gitrepo_export/locale/de/LC_MESSAGES/djangojs.po
fiduswriter/gitrepo_export/locale/es/LC_MESSAGES/djangojs.mo
fiduswriter/gitrepo_export/locale/es/LC_MESSAGES/djangojs.po
fiduswriter/gitrepo_export/locale/fr/LC_MESSAGES/djangojs.mo
fiduswriter/gitrepo_export/locale/fr/LC_MESSAGES/djangojs.po
fiduswriter/gitrepo_export/locale/it/LC_MESSAGES/djangojs.mo
fiduswriter/gitrepo_export/locale/it/LC_MESSAGES/djangojs.po
fiduswriter/gitrepo_export/locale/pt_BR/LC_MESSAGES/djangojs.mo
fiduswriter/gitrepo_export/locale/pt_BR/LC_MESSAGES/djangojs.po
fiduswriter/gitrepo_export/migrations/0001_initial.py
fiduswriter/gitrepo_export/migrations/0002_bookrepository_export_docx_bookrepository_export_odt.py
fiduswriter/gitrepo_export/migrations/__init__.py
fiduswriter/gitrepo_export/static/js/modules/gitrepo_export/books_overview.js
fiduswriter/gitrepo_export/static/js/modules/gitrepo_export/index.js
fiduswriter/gitrepo_export/static/js/modules/gitrepo_export/templates.js
fiduswriter/gitrepo_export/static/js/modules/gitrepo_export/tools.js
fiduswriter/gitrepo_export/static/js/modules/gitrepo_export/github/book_exporters.js
fiduswriter/gitrepo_export/static/js/modules/gitrepo_export/github/book_processor.js
fiduswriter/gitrepo_export/static/js/modules/gitrepo_export/github/index.js
fiduswriter/gitrepo_export/static/js/modules/gitrepo_export/github/tools/commit_file.js
fiduswriter_gitrepo_export-4.0.0.dist-info/licenses/LICENSE
fiduswriter_gitrepo_export-4.0.0.dist-info/METADATA
fiduswriter_gitrepo_export-4.0.0.dist-info/WHEEL
fiduswriter_gitrepo_export-4.0.0.dist-info/top_level.txt
fiduswriter_gitrepo_export-4.0.0.dist-info/RECORD
