Metadata-Version: 2.4
Name: fiduswriter-gitrepo-export
Version: 4.0.0
Summary: A Fidus Writer plugin to allow publishing of books to a Gitlab/Github repository.
Author-email: Johannes Wilm <johannes@fiduswriter.org>
License: AGPL-3.0-or-later
Project-URL: repository, https://www.github.com/fiduswriter/fiduswriter-gitrepo-export
Classifier: Environment :: Web Environment
Classifier: Framework :: Django
Classifier: Framework :: Django :: 4.2
Classifier: Intended Audience :: Developers
Classifier: License :: OSI Approved :: GNU Affero General Public License v3
Classifier: Operating System :: OS Independent
Classifier: Programming Language :: Python
Classifier: Programming Language :: Python :: 3
Classifier: Topic :: Internet :: WWW/HTTP
Classifier: Topic :: Internet :: WWW/HTTP :: Dynamic Content
License-File: LICENSE
Dynamic: license-file
